protstruc/__init__.py
protstruc/alphabet.py
protstruc/decorator.py
protstruc/general.py
protstruc/geometry.py
protstruc/io.py
protstruc/pdb.py
protstruc/protstruc.py
protstruc/constants/__init__.py
protstruc/constants/ideal.py
protstruc-0.0.7.dist-info/LICENSE
protstruc-0.0.7.dist-info/METADATA
protstruc-0.0.7.dist-info/WHEEL
protstruc-0.0.7.dist-info/top_level.txt
protstruc-0.0.7.dist-info/RECORD
